reqsim/__init__.py
reqsim/cli.py
reqsim/core.py
reqsim-0.1.0.dist-info/METADATA
reqsim-0.1.0.dist-info/WHEEL
reqsim-0.1.0.dist-info/entry_points.txt
reqsim-0.1.0.dist-info/top_level.txt
reqsim-0.1.0.dist-info/RECORD
