Metadata-Version: 2.4
Name: reqsim
Version: 0.1.0
Summary: A lightweight HTTP request simulator and API benchmark tool
Author: Baning Philip Amponsah
Author-email: baningphilip@gmail.com
Requires-Python: >=3.8
Requires-Dist: aiohttp
Dynamic: author
Dynamic: author-email
Dynamic: requires-dist
Dynamic: requires-python
Dynamic: summary
